quantized_mesh_encoder-0.5.0.dist-info/RECORD
quantized_mesh_encoder-0.5.0.dist-info/WHEEL
quantized_mesh_encoder-0.5.0.dist-info/top_level.txt
quantized_mesh_encoder-0.5.0.dist-info/METADATA
quantized_mesh_encoder-0.5.0.dist-info/licenses/LICENSE
quantized_mesh_encoder/encode.py
quantized_mesh_encoder/occlusion.py
quantized_mesh_encoder/ellipsoid.py
quantized_mesh_encoder/util.py
quantized_mesh_encoder/util_cy.cpython-310-darwin.so
quantized_mesh_encoder/constants.py
quantized_mesh_encoder/bounding_sphere.py
quantized_mesh_encoder/__init__.py
quantized_mesh_encoder/util_cy.pyx
quantized_mesh_encoder/util_cy.c
quantized_mesh_encoder/extensions.py
quantized_mesh_encoder/py.typed
quantized_mesh_encoder/ecef.py
quantized_mesh_encoder/normals.py
quantized_mesh_encoder/util_cy.pyi
