Metadata-Version: 2.4
Name: quantized-mesh-encoder
Version: 0.5.0
Summary: A fast Python Quantized Mesh encoder
Home-page: https://github.com/kylebarron/quantized-mesh-encoder
Author: Kyle Barron
Author-email: kylebarron2@gmail.com
License: MIT
Keywords: mesh heightmap elevation terrain numpy
Classifier: Intended Audience :: Information Technology
Classifier: Intended Audience :: Science/Research
Classifier: License :: OSI Approved :: MIT License
Classifier: Programming Language :: Python :: 3.6
Classifier: Programming Language :: Python :: 3.7
Classifier: Programming Language :: Python :: 3.8
Classifier: Topic :: Scientific/Engineering :: GIS
Requires-Python: >=3.9
License-File: LICENSE
Requires-Dist: numpy
Requires-Dist: attrs
Provides-Extra: test
Requires-Dist: pytest; extra == "test"
Requires-Dist: pytest-benchmark; extra == "test"
Requires-Dist: imageio; extra == "test"
Requires-Dist: quantized-mesh-tile; extra == "test"
Dynamic: author
Dynamic: author-email
Dynamic: classifier
Dynamic: description
Dynamic: description-content-type
Dynamic: home-page
Dynamic: keywords
Dynamic: license
Dynamic: license-file
Dynamic: provides-extra
Dynamic: requires-dist
Dynamic: requires-python
Dynamic: summary
